ddalg/__init__.py
ddalg/itree/__init__.py
ddalg/itree/_itree.py
ddalg/itree/test__itree.py
ddalg-0.0.1.dist-info/DESCRIPTION.rst
ddalg-0.0.1.dist-info/METADATA
ddalg-0.0.1.dist-info/RECORD
ddalg-0.0.1.dist-info/WHEEL
ddalg-0.0.1.dist-info/metadata.json
ddalg-0.0.1.dist-info/top_level.txt
