Metadata-Version: 2.0
Name: ddalg
Version: 0.0.1
Summary: Algorithms and data structures for my Python projects
Home-page: https://github.com/ielis/ddalg
Author: Daniel Danis
Author-email: daniel.gordon.danis@gmail.com
License: GPLv3
Keywords: algorithms python
Platform: UNKNOWN
Requires-Dist: numpy (>=1.18.2)
